Lab1/Lab1-2/myComparator_4bit.v
/*This module describes a 4-bit comparator which compares two 4-bit numbers and outputs: 
    1 if they are equal
    0 if they are not equal
*/

module comparator_4bit(         //Creating a new module for comparator
    input [3:0] A,B,            //Declaring 4-bit bus for each input port
    output      Y               //Declaring 1-bit wire for output port
);
    wire [3:0] w;               //Declaring a 4-bit bus for internal connection
    assign w=~(A^B);            //Taking bitwise XNOR of the two inputs to check if individual bits are equal
    assign Y=&w;                //Taking AND of individual outputs to check if all bits are simultaneously equal
endmodule

Lab1/Lab1-2/myComparator_4bit_tb.v
/* This module serves as a test bench for 4-bit comparator by applying all possible values of
    of inputs one by one.
*/

`include "myComparator_4bit.v"                  //including the file which contains our comapartor module

module tb;                                      //creating a new module to act as test bench
    reg [3:0] A,B;                              //declaring registries to store values and act as inputs
    wire Y;                                     //declaring a wire to connect to output of comparator
    integer i,j;                                //loop variables for 'for' loop to provide test cases

    comparator_4bit comparator_4bit_module1(    //create an instance of our comparator
        .A(A),                                  //connecting 1st input bus to 1st registry
        .B(B),                                  //connecting 1st input bus to 2nd registry
        .Y(Y)                                   //connecting a wire to output of comparator
    );

    initial                                     //code in this block is sequentially executed to give test conditions
    begin                                       //start of block
        $dumpfile("myComparator_4bit.vcd");     //specifying the file to save the results
        $dumpvars(0,tb);                        //specifying that variables of module 'tb' should be saved
        A[3:0]=0;                               
        B[3:0]=0;                               //give initial values to avoid the inputs being in an unknown state in 1st second
        for(i=0;i<16;i=i+1)                     //nested for loop to sequentially give all possible input combinations
        begin
            for(j=0;j<16;j=j+1)
            begin
                #1
                A[3:0]=i;                       //decimal number is implicitly converted into binary and are stored in registries
                B[3:0]=j;
            end
        end
    end                                         //end of block
endmodule

Lab1/Lab1-2/myComparator_4bit.vcd
$date
	Thu Jul 31 13:47:24 2025
$end
$version
	Icarus Verilog
$end
$timescale
	1s
$end
$scope module tb $end
$var wire 1 ! Y $end
$var reg 4 " A [3:0] $end
$var reg 4 # B [3:0] $end
$var integer 32 $ i [31:0] $end
$var integer 32 % j [31:0] $end
$scope module comparator_4bit_module1 $end
$var wire 4 & A [3:0] $end
$var wire 4 ' B [3:0] $end
$var wire 4 ( w [3:0] $end
$var wire 1 ! Y $end
$upscope $end
$upscope $end
$enddefinitions $end
$comment Show the parameter values. $end
$dumpall
$end
#0
$dumpvars
b1111 (
b0 '
b0 &
b0 %
b0 $
b0 #
b0 "
1!
$end
#1
b1 %
#2
0!
b1110 (
b10 %
b1 #
b1 '
#3
b1101 (
b11 %
b10 #
b10 '
#4
b1100 (
b100 %
b11 #
b11 '
#5
b1011 (
b101 %
b100 #
b100 '
#6
b1010 (
b110 %
b101 #
b101 '
#7
b1001 (
b111 %
b110 #
b110 '
#8
b1000 (
b1000 %
b111 #
b111 '
#9
b111 (
b1001 %
b1000 #
b1000 '
#10
b110 (
b1010 %
b1001 #
b1001 '
#11
b101 (
b1011 %
b1010 #
b1010 '
#12
b100 (
b1100 %
b1011 #
b1011 '
#13
b11 (
b1101 %
b1100 #
b1100 '
#14
b10 (
b1110 %
b1101 #
b1101 '
#15
b1 (
b1111 %
b1110 #
b1110 '
#16
b0 (
b1 $
b0 %
b1111 #
b1111 '
#17
b1110 (
b1 %
b0 #
b0 '
b1 "
b1 &
#18
1!
b1111 (
b10 %
b1 #
b1 '
#19
0!
b1100 (
b11 %
b10 #
b10 '
#20
b1101 (
b100 %
b11 #
b11 '
#21
b1010 (
b101 %
b100 #
b100 '
#22
b1011 (
b110 %
b101 #
b101 '
#23
b1000 (
b111 %
b110 #
b110 '
#24
b1001 (
b1000 %
b111 #
b111 '
#25
b110 (
b1001 %
b1000 #
b1000 '
#26
b111 (
b1010 %
b1001 #
b1001 '
#27
b100 (
b1011 %
b1010 #
b1010 '
#28
b101 (
b1100 %
b1011 #
b1011 '
#29
b10 (
b1101 %
b1100 #
b1100 '
#30
b11 (
b1110 %
b1101 #
b1101 '
#31
b0 (
b1111 %
b1110 #
b1110 '
#32
b1 (
b10 $
b0 %
b1111 #
b1111 '
#33
b1101 (
b1 %
b0 #
b0 '
b10 "
b10 &
#34
b1100 (
b10 %
b1 #
b1 '
#35
1!
b1111 (
b11 %
b10 #
b10 '
#36
0!
b1110 (
b100 %
b11 #
b11 '
#37
b1001 (
b101 %
b100 #
b100 '
#38
b1000 (
b110 %
b101 #
b101 '
#39
b1011 (
b111 %
b110 #
b110 '
#40
b1010 (
b1000 %
b111 #
b111 '
#41
b101 (
b1001 %
b1000 #
b1000 '
#42
b100 (
b1010 %
b1001 #
b1001 '
#43
b111 (
b1011 %
b1010 #
b1010 '
#44
b110 (
b1100 %
b1011 #
b1011 '
#45
b1 (
b1101 %
b1100 #
b1100 '
#46
b0 (
b1110 %
b1101 #
b1101 '
#47
b11 (
b1111 %
b1110 #
b1110 '
#48
b10 (
b11 $
b0 %
b1111 #
b1111 '
#49
b1100 (
b1 %
b0 #
b0 '
b11 "
b11 &
#50
b1101 (
b10 %
b1 #
b1 '
#51
b1110 (
b11 %
b10 #
b10 '
#52
1!
b1111 (
b100 %
b11 #
b11 '
#53
0!
b1000 (
b101 %
b100 #
b100 '
#54
b1001 (
b110 %
b101 #
b101 '
#55
b1010 (
b111 %
b110 #
b110 '
#56
b1011 (
b1000 %
b111 #
b111 '
#57
b100 (
b1001 %
b1000 #
b1000 '
#58
b101 (
b1010 %
b1001 #
b1001 '
#59
b110 (
b1011 %
b1010 #
b1010 '
#60
b111 (
b1100 %
b1011 #
b1011 '
#61
b0 (
b1101 %
b1100 #
b1100 '
#62
b1 (
b1110 %
b1101 #
b1101 '
#63
b10 (
b1111 %
b1110 #
b1110 '
#64
b11 (
b100 $
b0 %
b1111 #
b1111 '
#65
b1011 (
b1 %
b0 #
b0 '
b100 "
b100 &
#66
b1010 (
b10 %
b1 #
b1 '
#67
b1001 (
b11 %
b10 #
b10 '
#68
b1000 (
b100 %
b11 #
b11 '
#69
1!
b1111 (
b101 %
b100 #
b100 '
#70
0!
b1110 (
b110 %
b101 #
b101 '
#71
b1101 (
b111 %
b110 #
b110 '
#72
b1100 (
b1000 %
b111 #
b111 '
#73
b11 (
b1001 %
b1000 #
b1000 '
#74
b10 (
b1010 %
b1001 #
b1001 '
#75
b1 (
b1011 %
b1010 #
b1010 '
#76
b0 (
b1100 %
b1011 #
b1011 '
#77
b111 (
b1101 %
b1100 #
b1100 '
#78
b110 (
b1110 %
b1101 #
b1101 '
#79
b101 (
b1111 %
b1110 #
b1110 '
#80
b100 (
b101 $
b0 %
b1111 #
b1111 '
#81
b1010 (
b1 %
b0 #
b0 '
b101 "
b101 &
#82
b1011 (
b10 %
b1 #
b1 '
#83
b1000 (
b11 %
b10 #
b10 '
#84
b1001 (
b100 %
b11 #
b11 '
#85
b1110 (
b101 %
b100 #
b100 '
#86
1!
b1111 (
b110 %
b101 #
b101 '
#87
0!
b1100 (
b111 %
b110 #
b110 '
#88
b1101 (
b1000 %
b111 #
b111 '
#89
b10 (
b1001 %
b1000 #
b1000 '
#90
b11 (
b1010 %
b1001 #
b1001 '
#91
b0 (
b1011 %
b1010 #
b1010 '
#92
b1 (
b1100 %
b1011 #
b1011 '
#93
b110 (
b1101 %
b1100 #
b1100 '
#94
b111 (
b1110 %
b1101 #
b1101 '
#95
b100 (
b1111 %
b1110 #
b1110 '
#96
b101 (
b110 $
b0 %
b1111 #
b1111 '
#97
b1001 (
b1 %
b0 #
b0 '
b110 "
b110 &
#98
b1000 (
b10 %
b1 #
b1 '
#99
b1011 (
b11 %
b10 #
b10 '
#100
b1010 (
b100 %
b11 #
b11 '
#101
b1101 (
b101 %
b100 #
b100 '
#102
b1100 (
b110 %
b101 #
b101 '
#103
1!
b1111 (
b111 %
b110 #
b110 '
#104
0!
b1110 (
b1000 %
b111 #
b111 '
#105
b1 (
b1001 %
b1000 #
b1000 '
#106
b0 (
b1010 %
b1001 #
b1001 '
#107
b11 (
b1011 %
b1010 #
b1010 '
#108
b10 (
b1100 %
b1011 #
b1011 '
#109
b101 (
b1101 %
b1100 #
b1100 '
#110
b100 (
b1110 %
b1101 #
b1101 '
#111
b111 (
b1111 %
b1110 #
b1110 '
#112
b110 (
b111 $
b0 %
b1111 #
b1111 '
#113
b1000 (
b1 %
b0 #
b0 '
b111 "
b111 &
#114
b1001 (
b10 %
b1 #
b1 '
#115
b1010 (
b11 %
b10 #
b10 '
#116
b1011 (
b100 %
b11 #
b11 '
#117
b1100 (
b101 %
b100 #
b100 '
#118
b1101 (
b110 %
b101 #
b101 '
#119
b1110 (
b111 %
b110 #
b110 '
#120
1!
b1111 (
b1000 %
b111 #
b111 '
#121
0!
b0 (
b1001 %
b1000 #
b1000 '
#122
b1 (
b1010 %
b1001 #
b1001 '
#123
b10 (
b1011 %
b1010 #
b1010 '
#124
b11 (
b1100 %
b1011 #
b1011 '
#125
b100 (
b1101 %
b1100 #
b1100 '
#126
b101 (
b1110 %
b1101 #
b1101 '
#127
b110 (
b1111 %
b1110 #
b1110 '
#128
b111 (
b1000 $
b0 %
b1111 #
b1111 '
#129
b1 %
b0 #
b0 '
b1000 "
b1000 &
#130
b110 (
b10 %
b1 #
b1 '
#131
b101 (
b11 %
b10 #
b10 '
#132
b100 (
b100 %
b11 #
b11 '
#133
b11 (
b101 %
b100 #
b100 '
#134
b10 (
b110 %
b101 #
b101 '
#135
b1 (
b111 %
b110 #
b110 '
#136
b0 (
b1000 %
b111 #
b111 '
#137
1!
b1111 (
b1001 %
b1000 #
b1000 '
#138
0!
b1110 (
b1010 %
b1001 #
b1001 '
#139
b1101 (
b1011 %
b1010 #
b1010 '
#140
b1100 (
b1100 %
b1011 #
b1011 '
#141
b1011 (
b1101 %
b1100 #
b1100 '
#142
b1010 (
b1110 %
b1101 #
b1101 '
#143
b1001 (
b1111 %
b1110 #
b1110 '
#144
b1000 (
b1001 $
b0 %
b1111 #
b1111 '
#145
b110 (
b1 %
b0 #
b0 '
b1001 "
b1001 &
#146
b111 (
b10 %
b1 #
b1 '
#147
b100 (
b11 %
b10 #
b10 '
#148
b101 (
b100 %
b11 #
b11 '
#149
b10 (
b101 %
b100 #
b100 '
#150
b11 (
b110 %
b101 #
b101 '
#151
b0 (
b111 %
b110 #
b110 '
#152
b1 (
b1000 %
b111 #
b111 '
#153
b1110 (
b1001 %
b1000 #
b1000 '
#154
1!
b1111 (
b1010 %
b1001 #
b1001 '
#155
0!
b1100 (
b1011 %
b1010 #
b1010 '
#156
b1101 (
b1100 %
b1011 #
b1011 '
#157
b1010 (
b1101 %
b1100 #
b1100 '
#158
b1011 (
b1110 %
b1101 #
b1101 '
#159
b1000 (
b1111 %
b1110 #
b1110 '
#160
b1001 (
b1010 $
b0 %
b1111 #
b1111 '
#161
b101 (
b1 %
b0 #
b0 '
b1010 "
b1010 &
#162
b100 (
b10 %
b1 #
b1 '
#163
b111 (
b11 %
b10 #
b10 '
#164
b110 (
b100 %
b11 #
b11 '
#165
b1 (
b101 %
b100 #
b100 '
#166
b0 (
b110 %
b101 #
b101 '
#167
b11 (
b111 %
b110 #
b110 '
#168
b10 (
b1000 %
b111 #
b111 '
#169
b1101 (
b1001 %
b1000 #
b1000 '
#170
b1100 (
b1010 %
b1001 #
b1001 '
#171
1!
b1111 (
b1011 %
b1010 #
b1010 '
#172
0!
b1110 (
b1100 %
b1011 #
b1011 '
#173
b1001 (
b1101 %
b1100 #
b1100 '
#174
b1000 (
b1110 %
b1101 #
b1101 '
#175
b1011 (
b1111 %
b1110 #
b1110 '
#176
b1010 (
b1011 $
b0 %
b1111 #
b1111 '
#177
b100 (
b1 %
b0 #
b0 '
b1011 "
b1011 &
#178
b101 (
b10 %
b1 #
b1 '
#179
b110 (
b11 %
b10 #
b10 '
#180
b111 (
b100 %
b11 #
b11 '
#181
b0 (
b101 %
b100 #
b100 '
#182
b1 (
b110 %
b101 #
b101 '
#183
b10 (
b111 %
b110 #
b110 '
#184
b11 (
b1000 %
b111 #
b111 '
#185
b1100 (
b1001 %
b1000 #
b1000 '
#186
b1101 (
b1010 %
b1001 #
b1001 '
#187
b1110 (
b1011 %
b1010 #
b1010 '
#188
1!
b1111 (
b1100 %
b1011 #
b1011 '
#189
0!
b1000 (
b1101 %
b1100 #
b1100 '
#190
b1001 (
b1110 %
b1101 #
b1101 '
#191
b1010 (
b1111 %
b1110 #
b1110 '
#192
b1011 (
b1100 $
b0 %
b1111 #
b1111 '
#193
b11 (
b1 %
b0 #
b0 '
b1100 "
b1100 &
#194
b10 (
b10 %
b1 #
b1 '
#195
b1 (
b11 %
b10 #
b10 '
#196
b0 (
b100 %
b11 #
b11 '
#197
b111 (
b101 %
b100 #
b100 '
#198
b110 (
b110 %
b101 #
b101 '
#199
b101 (
b111 %
b110 #
b110 '
#200
b100 (
b1000 %
b111 #
b111 '
#201
b1011 (
b1001 %
b1000 #
b1000 '
#202
b1010 (
b1010 %
b1001 #
b1001 '
#203
b1001 (
b1011 %
b1010 #
b1010 '
#204
b1000 (
b1100 %
b1011 #
b1011 '
#205
1!
b1111 (
b1101 %
b1100 #
b1100 '
#206
0!
b1110 (
b1110 %
b1101 #
b1101 '
#207
b1101 (
b1111 %
b1110 #
b1110 '
#208
b1100 (
b1101 $
b0 %
b1111 #
b1111 '
#209
b10 (
b1 %
b0 #
b0 '
b1101 "
b1101 &
#210
b11 (
b10 %
b1 #
b1 '
#211
b0 (
b11 %
b10 #
b10 '
#212
b1 (
b100 %
b11 #
b11 '
#213
b110 (
b101 %
b100 #
b100 '
#214
b111 (
b110 %
b101 #
b101 '
#215
b100 (
b111 %
b110 #
b110 '
#216
b101 (
b1000 %
b111 #
b111 '
#217
b1010 (
b1001 %
b1000 #
b1000 '
#218
b1011 (
b1010 %
b1001 #
b1001 '
#219
b1000 (
b1011 %
b1010 #
b1010 '
#220
b1001 (
b1100 %
b1011 #
b1011 '
#221
b1110 (
b1101 %
b1100 #
b1100 '
#222
1!
b1111 (
b1110 %
b1101 #
b1101 '
#223
0!
b1100 (
b1111 %
b1110 #
b1110 '
#224
b1101 (
b1110 $
b0 %
b1111 #
b1111 '
#225
b1 (
b1 %
b0 #
b0 '
b1110 "
b1110 &
#226
b0 (
b10 %
b1 #
b1 '
#227
b11 (
b11 %
b10 #
b10 '
#228
b10 (
b100 %
b11 #
b11 '
#229
b101 (
b101 %
b100 #
b100 '
#230
b100 (
b110 %
b101 #
b101 '
#231
b111 (
b111 %
b110 #
b110 '
#232
b110 (
b1000 %
b111 #
b111 '
#233
b1001 (
b1001 %
b1000 #
b1000 '
#234
b1000 (
b1010 %
b1001 #
b1001 '
#235
b1011 (
b1011 %
b1010 #
b1010 '
#236
b1010 (
b1100 %
b1011 #
b1011 '
#237
b1101 (
b1101 %
b1100 #
b1100 '
#238
b1100 (
b1110 %
b1101 #
b1101 '
#239
1!
b1111 (
b1111 %
b1110 #
b1110 '
#240
0!
b1110 (
b1111 $
b0 %
b1111 #
b1111 '
#241
b0 (
b1 %
b0 #
b0 '
b1111 "
b1111 &
#242
b1 (
b10 %
b1 #
b1 '
#243
b10 (
b11 %
b10 #
b10 '
#244
b11 (
b100 %
b11 #
b11 '
#245
b100 (
b101 %
b100 #
b100 '
#246
b101 (
b110 %
b101 #
b101 '
#247
b110 (
b111 %
b110 #
b110 '
#248
b111 (
b1000 %
b111 #
b111 '
#249
b1000 (
b1001 %
b1000 #
b1000 '
#250
b1001 (
b1010 %
b1001 #
b1001 '
#251
b1010 (
b1011 %
b1010 #
b1010 '
#252
b1011 (
b1100 %
b1011 #
b1011 '
#253
b1100 (
b1101 %
b1100 #
b1100 '
#254
b1101 (
b1110 %
b1101 #
b1101 '
#255
b1110 (
b1111 %
b1110 #
b1110 '
#256
1!
b1111 (
b10000 $
b10000 %
b1111 #
b1111 '
