Lab2/problem3-vending/vending_mealy.v
// Vending Machine Mealy FSM
// Accepts coins of 5 or 10, vends when total >= 20, returns 5-change if total==25.
// States: sums 0, 5, 10, 15. Mealy outputs depend on state+coin.

module vending_mealy(
    input wire clk,
    input wire rst,                // active-high synchronous reset
    input wire [1:0] coin,         // 01=5, 10=10, 00=idle, (11 ignored)
    output reg dispense,           // 1 clk pulse when item dispensed
    output reg chg5                // 1 clk pulse when returning 5 change
);

    // State encoding for balance
    localparam S0 = 2'b00, // 0
               S5 = 2'b01, // 5
               S10 = 2'b10,// 10
               S15 = 2'b11;// 15

    reg [1:0] state, next_state;

    // Mealy outputs (combinational)
    reg dispense_comb, chg5_comb;

    // Next state logic and outputs
    always @(*) begin
        // Defaults
        next_state = state;
        dispense_comb = 0;
        chg5_comb = 0;

        case (state)
            S0: begin
                // Need minimum 20, ignore coin=00 and coin=11
                case (coin)
                    2'b01: next_state = S5;      // Insert 5
                    2'b10: next_state = S10;     // Insert 10
                    default: next_state = S0;
                endcase
            end
            S5: begin
                case (coin)
                    2'b01: next_state = S10;
                    2'b10: next_state = S15;
                    default: next_state = S5;
                endcase
            end
            S10: begin
                case (coin)
                    2'b01: next_state = S15;
                    2'b10: begin
                        next_state = S0;           // 10+10=20, vend!
                        dispense_comb = 1;
                    end
                    default: next_state = S10;
                endcase
            end
            S15: begin
                case (coin)
                    2'b01: begin
                        // 15+5=20, vend!
                        next_state = S0;
                        dispense_comb = 1;
                    end
                    2'b10: begin
                        // 15+10=25, vend + change
                        next_state = S0;
                        dispense_comb = 1;
                        chg5_comb = 1;
                    end
                    default: next_state = S15;
                endcase
            end
            default: next_state = S0;
        endcase
    end

    // Sequential state update and Mealy output register
    always @(posedge clk) begin
        if (rst) begin
            state <= S0;
            dispense <= 0;
            chg5 <= 0;
        end else begin
            state <= next_state;
            dispense <= dispense_comb;
            chg5 <= chg5_comb;
        end
    end

endmodule

Lab2/problem3-vending/tb_vending_mealy.v
// Testbench for vending_mealy; generates VCD, no terminal output.
`include "vending_mealy.v"
`timescale 1ns/1ps

module tb_vending_mealy;
    reg clk;
    reg rst;
    reg [1:0] coin;
    wire dispense;
    wire chg5;

    // DUT instantiation
    vending_mealy dut (
        .clk(clk),
        .rst(rst),
        .coin(coin),
        .dispense(dispense),
        .chg5(chg5)
    );

    // Clock generation: 10ns period (100 MHz)
    initial clk = 0;
    always #5 clk = ~clk;

    initial begin
        $dumpfile("vending_mealy.vcd");
        $dumpvars(0, tb_vending_mealy);

        // Reset and initial idle
        rst = 1; coin = 2'b00;
        #30;
        rst = 0;

        // Sequence: 5, 5, 10 (==20): vend
        coin = 2'b01; #10; coin = 2'b00; #10;
        coin = 2'b01; #10; coin = 2'b00; #10;
        coin = 2'b10; #10; coin = 2'b00; #10; // vend expected

        // Sequence: 10, 10 (==20): vend
        coin = 2'b10; #10; coin = 2'b00; #10;
        coin = 2'b10; #10; coin = 2'b00; #10; // vend expected

        // Sequence: 5, 5, 5, 10 (==25): vend + chg5
        coin = 2'b01; #10; coin = 2'b00; #10;
        coin = 2'b01; #10; coin = 2'b00; #10;
        coin = 2'b01; #10; coin = 2'b00; #10;
        coin = 2'b10; #10; coin = 2'b00; #10; // vend and chg5 expected

        // Idle, coin=00 and coin=11 ignored
        coin = 2'b00; #20;
        coin = 2'b11; #20;

        // End simulation
        #100;
        $finish;
    end

endmodule

Lab2/problem3-vending/vending_mealy.vcd
$date
	Tue Aug 19 11:23:09 2025
$end
$version
	Icarus Verilog
$end
$timescale
	1ps
$end
$scope module tb_vending_mealy $end
$var wire 1 ! dispense $end
$var wire 1 " chg5 $end
$var reg 1 # clk $end
$var reg 2 $ coin [1:0] $end
$var reg 1 % rst $end
$scope module dut $end
$var wire 1 # clk $end
$var wire 2 & coin [1:0] $end
$var wire 1 % rst $end
$var parameter 2 ' S0 $end
$var parameter 2 ( S10 $end
$var parameter 2 ) S15 $end
$var parameter 2 * S5 $end
$var reg 1 " chg5 $end
$var reg 1 + chg5_comb $end
$var reg 1 ! dispense $end
$var reg 1 , dispense_comb $end
$var reg 2 - next_state [1:0] $end
$var reg 2 . state [1:0] $end
$upscope $end
$upscope $end
$enddefinitions $end
$comment Show the parameter values. $end
$dumpall
b1 *
b11 )
b10 (
b0 '
$end
#0
$dumpvars
bx .
b0 -
0,
0+
b0 &
1%
b0 $
0#
x"
x!
$end
#5000
0"
0!
b0 .
1#
#10000
0#
#15000
1#
#20000
0#
#25000
1#
#30000
b1 -
0#
b1 $
b1 &
0%
#35000
b10 -
b1 .
1#
#40000
b1 -
0#
b0 $
b0 &
#45000
1#
#50000
b10 -
0#
b1 $
b1 &
#55000
b11 -
b10 .
1#
#60000
b10 -
0#
b0 $
b0 &
#65000
1#
#70000
1,
b0 -
0#
b10 $
b10 &
#75000
b10 -
0,
1!
b0 .
1#
#80000
b0 -
0#
b0 $
b0 &
#85000
0!
1#
#90000
b10 -
0#
b10 $
b10 &
#95000
1,
b0 -
b10 .
1#
#100000
0,
b10 -
0#
b0 $
b0 &
#105000
1#
#110000
1,
b0 -
0#
b10 $
b10 &
#115000
b10 -
0,
1!
b0 .
1#
#120000
b0 -
0#
b0 $
b0 &
#125000
0!
1#
#130000
b1 -
0#
b1 $
b1 &
#135000
b10 -
b1 .
1#
#140000
b1 -
0#
b0 $
b0 &
#145000
1#
#150000
b10 -
0#
b1 $
b1 &
#155000
b11 -
b10 .
1#
#160000
b10 -
0#
b0 $
b0 &
#165000
1#
#170000
b11 -
0#
b1 $
b1 &
#175000
1,
b0 -
b11 .
1#
#180000
0,
b11 -
0#
b0 $
b0 &
#185000
1#
#190000
1+
1,
b0 -
0#
b10 $
b10 &
#195000
b10 -
0+
0,
1"
1!
b0 .
1#
#200000
b0 -
0#
b0 $
b0 &
#205000
0"
0!
1#
#210000
0#
#215000
1#
#220000
0#
#225000
1#
#230000
0#
b11 $
b11 &
