Lab2/problem1-seqdet/seq_detect_mealy.v
// Mealy sequence detector for "1101" with overlap, output 1-cycle pulse on detection.

module seq_detect_mealy(
    input wire clk,
    input wire rst,    // synchronous, active-high
    input wire din,    // serial input bit (one per clock)
    output reg y       // 1-cycle pulse on ...1101 pattern
);

    // State encoding (tracks progress on "1101")
    localparam S0 = 2'b00,  // initial (no match yet)
               S1 = 2'b01,  // seen '1'
               S2 = 2'b10,  // seen "11"
               S3 = 2'b11;  // seen "110"

    reg [1:0] state, next_state;
    reg y_comb;

    // Next state and Mealy output logic
    always @(*) begin
        next_state = state;
        y_comb = 0;

        case (state)
            S0: begin
                if (din)
                    next_state = S1;
                else
                    next_state = S0;
            end
            S1: begin
                if (din)
                    next_state = S2;
                else
                    next_state = S0;
            end
            S2: begin
                if (din)
                    next_state = S2; // Stay in S2 (overlap on '1')
                else
                    next_state = S3;
            end
            S3: begin
                if (din) begin
                    next_state = S1; // Overlap: first '1' of next possible pattern
                    y_comb = 1;      // Detected "1101"!
                end else begin
                    next_state = S0;
                end
            end
            default: next_state = S0;
        endcase
    end

    // Registers
    always @(posedge clk) begin
        if (rst) begin
            state <= S0;
            y <= 0;
        end else begin
            state <= next_state;
            y <= y_comb;
        end
    end

endmodule

Lab2/problem1-seqdet/tb_seq_detect_mealy.v
// Testbench for seq_detect_mealy; drives overlapping pattern bits
`timescale 1ns/1ps
`include "seq_detect_mealy.v"

module tb_seq_detect_mealy;
    reg clk;
    reg rst;
    reg din;
    wire y;

    // Instantiate DUT
    seq_detect_mealy dut (
        .clk(clk),
        .rst(rst),
        .din(din),
        .y(y)
    );

    // 100 MHz clock (period 10 ns)
    initial clk = 0;
    always #5 clk = ~clk;

    // Example input stream with overlaps: 1101101101
    reg [15:0] bitstream;
    integer i;

    initial begin
        $dumpfile("seq_detect_mealy.vcd");
        $dumpvars(0, tb_seq_detect_mealy);

        // Test pattern: multiple overlapping 1101s, also edges
        bitstream = 16'b0110110110110100; // Rightmost clock first: left aligns with time
        // Bit indices for expected output pulses: cycles 4, 8, 12

        rst = 1; din = 0;
        #20;
        rst = 0;

        // Play the stream (from bitstream[15]..bitstream)
        for (i = 15; i >= 0; i = i - 1) begin
            din = bitstream[i];
            #10;
        end

        // Some idle after pattern
        din = 0;
        #100;
        $finish;
    end

endmodule

Lab2/problem1-seqdet/seq_detect_mealy.vcd
$date
	Tue Aug 19 11:31:55 2025
$end
$version
	Icarus Verilog
$end
$timescale
	1ps
$end
$scope module tb_seq_detect_mealy $end
$var wire 1 ! y $end
$var reg 16 " bitstream [15:0] $end
$var reg 1 # clk $end
$var reg 1 $ din $end
$var reg 1 % rst $end
$var integer 32 & i [31:0] $end
$scope module dut $end
$var wire 1 # clk $end
$var wire 1 $ din $end
$var wire 1 % rst $end
$var parameter 2 ' S0 $end
$var parameter 2 ( S1 $end
$var parameter 2 ) S2 $end
$var parameter 2 * S3 $end
$var reg 2 + next_state [1:0] $end
$var reg 2 , state [1:0] $end
$var reg 1 ! y $end
$var reg 1 - y_comb $end
$upscope $end
$upscope $end
$enddefinitions $end
$comment Show the parameter values. $end
$dumpall
b11 *
b10 )
b1 (
b0 '
$end
#0
$dumpvars
0-
bx ,
b0 +
bx &
1%
0$
0#
b110110110110100 "
x!
$end
#5000
0!
b0 ,
1#
#10000
0#
#15000
1#
#20000
0#
b1111 &
0%
#25000
1#
#30000
b1 +
0#
1$
b1110 &
#35000
b10 +
b1 ,
1#
#40000
0#
b1101 &
#45000
b10 ,
1#
#50000
b11 +
0#
0$
b1100 &
#55000
b0 +
b11 ,
1#
#60000
1-
b1 +
0#
1$
b1011 &
#65000
b10 +
0-
1!
b1 ,
1#
#70000
0#
b1010 &
#75000
0!
b10 ,
1#
#80000
b11 +
0#
0$
b1001 &
#85000
b0 +
b11 ,
1#
#90000
1-
b1 +
0#
1$
b1000 &
#95000
b10 +
0-
1!
b1 ,
1#
#100000
0#
b111 &
#105000
0!
b10 ,
1#
#110000
b11 +
0#
0$
b110 &
#115000
b0 +
b11 ,
1#
#120000
1-
b1 +
0#
1$
b101 &
#125000
b10 +
0-
1!
b1 ,
1#
#130000
0#
b100 &
#135000
0!
b10 ,
1#
#140000
b11 +
0#
0$
b11 &
#145000
b0 +
b11 ,
1#
#150000
1-
b1 +
0#
1$
b10 &
#155000
b10 +
0-
1!
b1 ,
1#
#160000
b0 +
0#
0$
b1 &
#165000
0!
b0 ,
1#
#170000
0#
b0 &
#175000
1#
#180000
0#
b11111111111111111111111111111111 &
