Lab2/problem2-traffic/traffic_light.v
// Traffic Light Controller (Moore FSM)
// Controls NS/EW lights; NS green 5s, NS yellow 2s, EW green 5s, EW yellow 2s. Repeats.
// Inputs:
//   clk: system clock
//   rst: reset, synchronous, active-high
//   tick: 1 Hz pulse, 1 cycle wide
// Outputs: each direction's green/yellow/red, one active at a time

module traffic_light(
    input wire clk,
    input wire rst,
    input wire tick,
    output reg ns_g, ns_y, ns_r,
    output reg ew_g, ew_y, ew_r
);

    // State encoding for FSM
    localparam S_NS_G = 2'b00,   // North-South Green
               S_NS_Y = 2'b01,   // North-South Yellow
               S_EW_G = 2'b10,   // East-West Green
               S_EW_Y = 2'b11;   // East-West Yellow

    reg [1:0] state, next_state;
    reg [2:0] tick_count, next_tick_count; // up to 5

    // Next state and tick count logic
    always @(*) begin
        next_state = state;
        next_tick_count = tick_count;

        case (state)
            S_NS_G: begin
                if (tick) begin
                    if (tick_count == 3'd4) begin
                        next_state = S_NS_Y;
                        next_tick_count = 0;
                    end else begin
                        next_tick_count = tick_count + 1;
                    end
                end
            end
            S_NS_Y: begin
                if (tick) begin
                    if (tick_count == 3'd1) begin
                        next_state = S_EW_G;
                        next_tick_count = 0;
                    end else begin
                        next_tick_count = tick_count + 1;
                    end
                end
            end
            S_EW_G: begin
                if (tick) begin
                    if (tick_count == 3'd4) begin
                        next_state = S_EW_Y;
                        next_tick_count = 0;
                    end else begin
                        next_tick_count = tick_count + 1;
                    end
                end
            end
            S_EW_Y: begin
                if (tick) begin
                    if (tick_count == 3'd1) begin
                        next_state = S_NS_G;
                        next_tick_count = 0;
                    end else begin
                        next_tick_count = tick_count + 1;
                    end
                end
            end
            default: begin
                next_state = S_NS_G;
                next_tick_count = 0;
            end
        endcase
    end

    // Registers for state and tick counter
    always @(posedge clk) begin
        if (rst) begin
            state <= S_NS_G;
            tick_count <= 0;
        end else begin
            state <= next_state;
            tick_count <= next_tick_count;
        end
    end

    // Output logic (Moore machine: only depends on state)
    always @(*) begin
        // Default to all RED
        ns_g = 0; ns_y = 0; ns_r = 0;
        ew_g = 0; ew_y = 0; ew_r = 0;

        case (state)
            S_NS_G: begin
                ns_g = 1; ns_y = 0; ns_r = 0;
                ew_g = 0; ew_y = 0; ew_r = 1;
            end
            S_NS_Y: begin
                ns_g = 0; ns_y = 1; ns_r = 0;
                ew_g = 0; ew_y = 0; ew_r = 1;
            end
            S_EW_G: begin
                ns_g = 0; ns_y = 0; ns_r = 1;
                ew_g = 1; ew_y = 0; ew_r = 0;
            end
            S_EW_Y: begin
                ns_g = 0; ns_y = 0; ns_r = 1;
                ew_g = 0; ew_y = 1; ew_r = 0;
            end
            default: begin
                ns_g = 1; ns_y = 0; ns_r = 0;
                ew_g = 0; ew_y = 0; ew_r = 1;
            end
        endcase
    end

endmodule

Lab2/problem2-traffic/tb_traffic_light.v
// Testbench for traffic_light
// Generates clock, reset, and 1 Hz tick. Dumps output to VCD waveform file.

`include "traffic_light.v"
`timescale 1ns/1ps

module tb_traffic_light;
    reg clk;
    reg rst;
    reg tick;
    wire ns_g;
    wire ns_y;
    wire ns_r;
    wire ew_g;
    wire ew_y;
    wire ew_r;

    // Instantiate the DUT
    traffic_light dut (
        .clk(clk),
        .rst(rst),
        .tick(tick),
        .ns_g(ns_g),
        .ns_y(ns_y),
        .ns_r(ns_r),
        .ew_g(ew_g),
        .ew_y(ew_y),
        .ew_r(ew_r)
    );

    // 100 MHz clock generation (10 ns period)
    initial clk = 0;
    always #5 clk = ~clk;

    integer i;

    initial begin
        // Waveform dump settings for GTKWave
        $dumpfile("traffic_light.vcd");
        $dumpvars(0, tb_traffic_light);

        // Reset sequence
        rst = 1;
        tick = 0;
        #30;
        rst = 0;

        // Generate 36 ticks for simulation
        for (i = 0; i < 36; i = i + 1) begin
            tick = 1;
            #10;
            tick = 0;
            #990;
        end

        // Finish simulation after some delay
        #100;
        $finish;
    end

endmodule

Lab2/problem2-traffic/traffic_light.vcd
$date
	Tue Aug 19 11:05:15 2025
$end
$version
	Icarus Verilog
$end
$timescale
	1ps
$end
$scope module tb_traffic_light $end
$var wire 1 ! ns_y $end
$var wire 1 " ns_r $end
$var wire 1 # ns_g $end
$var wire 1 $ ew_y $end
$var wire 1 % ew_r $end
$var wire 1 & ew_g $end
$var reg 1 ' clk $end
$var reg 1 ( rst $end
$var reg 1 ) tick $end
$var integer 32 * i [31:0] $end
$scope module dut $end
$var wire 1 ' clk $end
$var wire 1 ( rst $end
$var wire 1 ) tick $end
$var parameter 2 + S_EW_G $end
$var parameter 2 , S_EW_Y $end
$var parameter 2 - S_NS_G $end
$var parameter 2 . S_NS_Y $end
$var reg 1 & ew_g $end
$var reg 1 % ew_r $end
$var reg 1 $ ew_y $end
$var reg 2 / next_state [1:0] $end
$var reg 3 0 next_tick_count [2:0] $end
$var reg 1 # ns_g $end
$var reg 1 " ns_r $end
$var reg 1 ! ns_y $end
$var reg 2 1 state [1:0] $end
$var reg 3 2 tick_count [2:0] $end
$upscope $end
$upscope $end
$enddefinitions $end
$comment Show the parameter values. $end
$dumpall
b1 .
b0 -
b11 ,
b10 +
$end
#0
$dumpvars
bx 2
bx 1
b0 0
b0 /
bx *
0)
1(
0'
x&
x%
x$
x#
x"
x!
$end
#5000
1%
0$
0&
0"
0!
1#
b0 2
b0 1
1'
#10000
0'
#15000
1'
#20000
0'
#25000
1'
#30000
b1 0
0'
1)
b0 *
0(
#35000
b10 0
b1 2
1'
#40000
b1 0
0'
0)
#45000
1'
#50000
0'
#55000
1'
#60000
0'
#65000
1'
#70000
0'
#75000
1'
#80000
0'
#85000
1'
#90000
0'
#95000
1'
#100000
0'
#105000
1'
#110000
0'
#115000
1'
#120000
0'
#125000
1'
#130000
0'
#135000
1'
#140000
0'
#145000
1'
#150000
0'
#155000
1'
#160000
0'
#165000
1'
#170000
0'
#175000
1'
#180000
0'
#185000
1'
#190000
0'
#195000
1'
#200000
0'
#205000
1'
#210000
0'
#215000
1'
#220000
0'
#225000
1'
#230000
0'
#235000
1'
#240000
0'
#245000
1'
#250000
0'
#255000
1'
#260000
0'
#265000
1'
#270000
0'
#275000
1'
#280000
0'
#285000
1'
#290000
0'
#295000
1'
#300000
0'
#305000
1'
#310000
0'
#315000
1'
#320000
0'
#325000
1'
#330000
0'
#335000
1'
#340000
0'
#345000
1'
#350000
0'
#355000
1'
#360000
0'
#365000
1'
#370000
0'
#375000
1'
#380000
0'
#385000
1'
#390000
0'
#395000
1'
#400000
0'
#405000
1'
#410000
0'
#415000
1'
#420000
0'
#425000
1'
#430000
0'
#435000
1'
#440000
0'
#445000
1'
#450000
0'
#455000
1'
#460000
0'
#465000
1'
#470000
0'
#475000
1'
#480000
0'
#485000
1'
#490000
0'
#495000
1'
#500000
0'
#505000
1'
#510000
0'
#515000
1'
#520000
0'
#525000
1'
#530000
0'
#535000
1'
#540000
0'
#545000
1'
#550000
0'
#555000
1'
#560000
0'
#565000
1'
#570000
0'
#575000
1'
#580000
0'
#585000
1'
#590000
0'
#595000
1'
#600000
0'
#605000
1'
#610000
0'
#615000
1'
#620000
0'
#625000
1'
#630000
0'
#635000
1'
#640000
0'
#645000
1'
#650000
0'
#655000
1'
#660000
0'
#665000
1'
#670000
0'
#675000
1'
#680000
0'
#685000
1'
#690000
0'
#695000
1'
#700000
0'
#705000
1'
#710000
0'
#715000
1'
#720000
0'
#725000
1'
#730000
0'
#735000
1'
#740000
0'
#745000
1'
#750000
0'
#755000
1'
#760000
0'
#765000
1'
#770000
0'
#775000
1'
#780000
0'
#785000
1'
#790000
0'
#795000
1'
#800000
0'
#805000
1'
#810000
0'
#815000
1'
#820000
0'
#825000
1'
#830000
0'
#835000
1'
#840000
0'
#845000
1'
#850000
0'
#855000
1'
#860000
0'
#865000
1'
#870000
0'
#875000
1'
#880000
0'
#885000
1'
#890000
0'
#895000
1'
#900000
0'
#905000
1'
#910000
0'
#915000
1'
#920000
0'
#925000
1'
#930000
0'
#935000
1'
#940000
0'
#945000
1'
#950000
0'
#955000
1'
#960000
0'
#965000
1'
#970000
0'
#975000
1'
#980000
0'
#985000
1'
#990000
0'
#995000
1'
#1000000
0'
#1005000
1'
#1010000
0'
#1015000
1'
#1020000
0'
#1025000
1'
#1030000
b10 0
0'
1)
b1 *
#1035000
b11 0
b10 2
1'
#1040000
b10 0
0'
0)
